aqmp/__init__.py
aqmp/aqmp.py
aqmp/basis.py
aqmp/main.py
aqmp/omp.py
aqmp/rawfile.py
aqmp/utility.py
aqmp_compressor-0.1.6.dist-info/METADATA
aqmp_compressor-0.1.6.dist-info/WHEEL
aqmp_compressor-0.1.6.dist-info/entry_points.txt
aqmp_compressor-0.1.6.dist-info/top_level.txt
aqmp_compressor-0.1.6.dist-info/RECORD
