Metadata-Version: 2.1
Name: aqmp-compressor
Version: 0.1.6
Summary: A Python package for compressing and decompressing images using OMP and wavelet transforms.
Home-page: https://github.com/Emmatassone/AQMP
Author: Emmanuel A. Tassone
Author-email: emmanueltassone@gmail.com
Classifier: Programming Language :: Python :: 3
Classifier: License :: OSI Approved :: MIT License
Classifier: Operating System :: OS Independent
Requires-Python: <=3.11, >=3.9
Requires-Dist: numpy
Requires-Dist: scikit-learn
Requires-Dist: Pillow
Requires-Dist: PyWavelets
Requires-Dist: anytree
